ystu/__init__.py
ystu/connect.py
ystu/parsers.py
ystu-0.0.7.dist-info/METADATA
ystu-0.0.7.dist-info/WHEEL
ystu-0.0.7.dist-info/top_level.txt
ystu-0.0.7.dist-info/RECORD
